Workbook

Sheet Final Summary
A1: 5 kWp Grid-Connected Rooftop Solar | Final Summary
A3: Purpose | B3: Mock techno-commercial case study | C3: Built for GET (Technical Sales/BD/PM) interview preparation - not a live customer engagement
A4: Technical Configuration
A5: Recommended configuration | B5: ='Load & Sizing'!B18&" x 575 Wp Waaree bifacial modules + Loom Solar Fusion 63 (6kW, 3-phase)" -> 9 x 575 Wp Waaree bifacial modules + Loom Solar Fusion 63 (6kW, 3-phase)
A6: DC system size (kWp) | B6: ='Load & Sizing'!B19 -> 5.175
A7: Estimated annual generation, Year 1 (kWh) | B7: ='Savings & Financial'!B7 -> 6799.95
A8: Generation yield check (kWh/kWp/yr) | B8: ='Savings & Financial'!B7/'Load & Sizing'!B19 -> 1314
A10: Commercial Summary
A11: Total direct project cost (Rs.) | B11: ='BOM & Costing'!E26 -> 248525.55
A12: Gross project price, before subsidy (Rs.) | B12: ='BOM & Costing'!E30 -> 278348.62
A13: PM Surya Ghar CFA applied (Rs.) | B13: ='BOM & Costing'!E34 -> 78000
A14: Net customer investment, after subsidy (Rs.) | B14: ='BOM & Costing'!E36 -> 200348.62
A16: Customer Economics
A17: Net annual savings, Year 1 (Rs.) | B17: ='Savings & Financial'!B19 -> 47309.634
A18: Simple payback (years) | B18: ='Savings & Financial'!B23 -> 4.2348376
A19: Approx. 25-year ROI on net investment | B19: ='Savings & Financial'!B29 -> 5.3041542
A21: Inverter Selection Note
A22: A Loom Solar Fusion 63 (6 kW, three-phase) was selected for this 5.175 kWp array, giving a DC/AC ratio of ~0.86 (below the typical 1.1-1.25 EPC target). This is a sizing trade-off made under the assumption of a three-phase customer connection and design headroom - see Component Selection for the full rationale and the single-phase alternative that was considered.

Sheet Read Me
A1: Solar Rooftop PV | Techno-Commercial Case Study
A3: Purpose
A4: A self-directed mock techno-commercial case study for a simulated residential rooftop solar customer, built to demonstrate the requirement-to-proposal workflow used in technical sales/BD roles. Not a live client engagement.
A6: How to read this workbook
A7: 1. Assumptions - all input assumptions in one place
A8: 2. Load & Sizing - why 5.175 kWp was chosen
A9: 3. Component Selection - module + inverter specs, string compatibility checks, and the sizing rationale (incl. DC/AC ratio)
A10: 4. BOM & Costing - full bill of materials, project cost, subsidy, net customer investment
A11: 5. Savings & Financial - annual savings, payback, ROI, 25-year view
A12: 6. Sensitivity - how tariff / generation / cost swings affect payback
A13: 7. Alternatives - comparison against 2 other configurations
A14: 8. Final Summary - one-page rollup, all values LINKED to source sheets (no duplicate hardcoding)
... A23: - PM Surya Ghar subsidy structure (Rs.30,000/kW for first 2kW, Rs.18,000/kW for 3rd kW, capped at Rs.78,000 for systems >=3kW residential) reflects official MNRE guidelines as of Sep 2026.

Sheet Assumptions
A1: Assumptions
A3: Customer Profile (simulated - clearly an assumption, not real data)
A4: Customer type | B4: Urban residential | C4: Homeowner with independent rooftop access | D4: Assumption
A5: Location | B5: Delhi-NCR (representative) | C5: Chosen for consistency with Vista's Noida base; irradiation assumption below reflects this region | D5: Assumption
A6: Avg. monthly electricity bill | B6: 5500 | C6: Used to size the system to a 'higher-consumption home' segment | D6: Assumption
A7: Assumed electricity tariff | B7: 8 | C7: Rs./kWh, mid-slab residential tariff typical for a Delhi-NCR high-consumption household | D7: Assumption
A8: Monthly consumption (derived) | B8: =B6/B7 -> 687.5 | C8: Bill / tariff | D8: Formula
A9: Usable shadow-free roof area | B9: 550-600 sq ft | C9: Enough for a ~5 kWp array at typical module footprint (~18 sq ft/module incl. spacing) | D9: Assumption
A10: Customer objective | B10: Reduce electricity bill; moderate upfront cost priority over max ROI | C10: Drives system sizing and component choice (mid-tier, not premium) | D10: Assumption
A11: Electrical connection | B11: Three-phase (see Component Selection note) | C11: Required for the corrected inverter pairing (Fusion 63) | D11: Assumption - flagged
A13: Technical / Generation Assumptions
A14: Peak sun hours (Delhi-NCR, representative) | B14: 4.5 | C14: hrs/day - conservative planning value for the region | D14: Assumption
A15: System performance ratio (PR) | B15: 0.8 | C15: Accounts for module/inverter/temperature/wiring/soiling losses combined - typical range 75-82% for well-maintained rooftop systems in India | D15: Assumption
A16: Module degradation (annual, after yr 1) | B16: 0.0055 | C16: 0.55%/yr - reflects Waaree's linear performance warranty profile | D16: Assumption
A17: O&M cost (annual) | B17: 2500 | C17: Cleaning + minor upkeep; on-grid systems have low O&M vs off-grid/hybrid | D17: Assumption
A18: Inverter replacement | B18: Assumed once, year 12 | C18: String inverters typically warrantied 5 yrs, useful life 10-15 yrs | D18: Assumption
A19: Self-consumption share of generation | B19: 0.55 | C19: Rest exported to grid under net metering; daytime household occupancy assumed moderate | D19: Assumption
A20: Net metering credit rate (for exported units) | B20: 6.5 | C20: Rs./kWh - typically at or below retail tariff under most DISCOM net-metering rules | D20: Assumption
A22: Government Policy (fact, not assumption)
A23: PM Surya Ghar CFA - 1st kW | B23: 30000 | C23: Rs./kW, official MNRE slab | D23: Fact
A24: PM Surya Ghar CFA - 2nd kW | B24: 30000 | C24: Rs./kW, official MNRE slab | D24: Fact
A25: PM Surya Ghar CFA - 3rd kW | B25: 18000 | C25: Rs./kW, official MNRE slab | D25: Fact
A26: Max residential CFA (systems >=3kW) | B26: 78000 | C26: Flat cap regardless of size beyond 3kW, per MNRE guidelines | D26: Fact
A27: Domestic content requirement | B27: Yes | C27: CFA requires domestically manufactured modules/cells - Waaree is domestic, so this system qualifies | D27: Fact

Sheet Load & Sizing
A1: Load & Requirement Analysis / System Sizing
A3: Step 1: Estimate load from the customer's bill
A4: Avg. monthly bill (Rs.) | B4: =Assumptions!B6 -> 5500
A5: Assumed tariff (Rs./kWh) | B5: =Assumptions!B7 -> 8
A6: Estimated monthly consumption (kWh) | B6: =B4/B5 -> 687.5
A7: Estimated annual consumption (kWh) | B7: =B6*12 -> 8250
A9: Step 2: Size the system to target ~80-90% of annual consumption offset
A10: Target offset of annual consumption | B10: 0.85 | C10: Full 100% offset would oversize the system versus roof area and budget constraints; 85% is a common practical target
A11: Target annual generation (kWh) | B11: =B7*B10 -> 7012.5
A12: Peak sun hours (from Assumptions) | B12: =Assumptions!B14 -> 4.5
A13: Performance ratio (from Assumptions) | B13: =Assumptions!B15 -> 0.8
A14: Indicative required capacity (kWp) | B14: =B11/(B12*365*B13) -> 5.336758 | C14: Target annual generation / (PSH x 365 x PR)
A16: Step 3: Fit to available module count and roof area
A17: Selected module rating (Wp) | B17: 575
A18: Number of modules selected | B18: 9 | C18: Rounds the indicative requirement to a whole number of modules that also fits the assumed roof area
A19: Resulting DC system size (kWp) | B19: =B17*B18/1000 -> 5.175
A20: Check vs. indicative requirement | B20: =IF(ABS(B19-B14)/B14<0.15,"Within 15% - acceptable fit","Review sizing") -> Within 15% - acceptable fit
A22: Why 5.175 kWp: the customer's bill (Rs.5,500/month at Rs.8/kWh) implies roughly 688 kWh/month, ~8,250 kWh/year of consumption. Targeting 85% offset needs roughly 4.9-5.0 kWp under Delhi-NCR irradiation (4.5 PSH, 80% PR). Nine 575 Wp modules give 5.175 kWp DC - the closest whole-module fit that also comfortably suits the assumed 550-600 sq ft roof area (9 modules at ~18 sq ft each with spacing = ~500-550 sq ft).

Sheet Component Selection
A1: Component Selection
A3: Module: Waaree BIN-08-575 (575 Wp, N-Type TOPCon, Bifacial, Dual-Glass)
A4: Rated power | B4: 575 Wp
A5: Technology | B5: N-Type TOPCon, bifacial, dual-glass, monocrystalline
A6: Cell count | B6: 144
A7: Rated efficiency | B7: 22.26%
A8: Voc (open-circuit voltage) | B8: 52.3 V | C8: Used below for string voltage compatibility check
A9: Isc (short-circuit current) | B9: 13.87 A | C9: Used below for inverter current compatibility check
A10: Dimensions | B10: ~2278 x 1134 x 33 mm
A11: Warranty | B11: 12-yr product / 30-yr linear power output (typical for this product class)
A12: Why this module | B12: Bifacial N-Type gives a modest generation uplift (typically 3-8%) from rear-side reflected light where the mounting allows some ground/roof reflectance and rear ventilation; the case study conservatively does NOT add a bifacial gain to the 6,800 kWh/year generation figure, since a flush/close-mounted residential roof install captures little rear-side gain in practice.
A14: Inverter Selection & Sizing Rationale
A15: This 5.175 kWp array is paired with a Loom Solar Fusion 63 (6 kW, three-phase) inverter. A smaller, single-phase inverter (~4 kW class) was also considered, since it would give a DC/AC ratio closer to the typical 1.1-1.25 EPC target. The 6 kW three-phase unit was selected instead under the assumption that the customer has (or will arrange) a three-phase connection, and to keep headroom against a Voc-derating margin. This is a sizing trade-off, not a technical error - both configurations are electrically valid for this array; the choice depends on the customer's actual electrical connection, which should be confirmed on-site before finalizing a real quotation.
A16: Alternative considered | B16: Single-phase ~4 kW-class inverter (e.g. Loom Solar Fusion 41) | C16: Would give a DC/AC ratio closer to ~1.15-1.29 depending on exact model, but max PV input power on this class (~4.5 kW) is close to or below the 5.175 kWp array - would need either a slight array de-rate or confirming the specific model's headroom before use.
A17: Selected inverter | B17: Loom Solar Fusion 63 (6 kW, three-phase) | C17: Spec used in this model: max PV input power 7.8 kW, max input voltage 1000 V, 2 MPPT trackers, max input current 40 A, 98.5% max efficiency
A18: Assumption this relies on | B18: Customer has, or will arrange, a three-phase electrical connection | C18: Reasonable for a higher-consumption home (the customer profile already assumed), and stated explicitly here as a design input rather than left implicit
A20: String voltage & current compatibility check (with selected inverter)
A21: String Voc (9 modules in series) | B21: 9 x 52.3 V = 470.7 V | C21: Well within Fusion 63's 1000 V max input - safe even with cold-weather Voc increase (~10-15%)
A22: String Isc | B22: 13.87 A | C22: Comfortably within Fusion 63's 40 A max input current
A23: DC/AC ratio | B23: 5.175 kWp / 6 kW = 0.86 | C23: Below the typical 1.1-1.25 target range for optimal inverter utilization. This reflects the three-phase/headroom design choice above rather than a sizing error - the array will never be clipped, but the inverter runs below its full rated capacity. Worth flagging as a trade-off if asked about cost-optimization.
A25: Inverter specs used (Loom Solar Fusion 63)
A26: Rated output power | B26: 6 kW
A27: Phase | B27: Three-phase, 400 V output
A28: Max PV input power | B28: 7.8 kW
A29: Max PV input voltage | B29: 1000 V
A30: MPPT trackers | B30: 2
A31: Max efficiency | B31: 98.5%
A32: Communication | B32: WiFi, GPRS, RS-485, RS-232 | C32: Enables remote generation monitoring - relevant to customer after-sales value prop
A33: Protection | B33: Anti-islanding, over-voltage/current/temp, DC reverse polarity, Type II SPD

Sheet BOM & Costing
A1: Bill of Materials & Project Costing
A3: Item | B3: Qty | C3: Unit | D3: Unit Cost (Rs.) | E3: Total Cost (Rs.) | F3: Basis
A4: Major Equipment
A5: Waaree 575 Wp N-Type bifacial module | B5: 9 | C5: nos | D5: 11299 | E5: =B5*D5 -> 101691 | F5: Public manufacturer/retail reference price
A6: Loom Solar Fusion 63 (6 kW, 3-phase inverter) | B6: 1 | C6: nos | D6: 42000 | E6: =B6*D6 -> 42000 | F6: Estimated from typical Rs./kW string-inverter market pricing (~Rs.7,000/kW); exact retail price for this SKU not independently confirmed
A7: Balance of System
A8: Aluminium/GI mounting structure | B8: 1 | C8: lot | D8: 25000 | E8: =B8*D8 -> 25000 | F8: Estimate; roof-type dependent
A9: 4 sq.mm DC solar cable | B9: 1 | C9: lot | D9: 7000 | E9: =B9*D9 -> 7000 | F9: Estimate anchored to current cable market listings
A10: AC cable + accessories | B10: 1 | C10: lot | D10: 5000 | E10: =B10*D10 -> 5000 | F10: Estimate
A11: MC4 connectors + DC isolator | B11: 1 | C11: lot | D11: 3500 | E11: =B11*D11 -> 3500 | F11: Estimate
A12: ACDB/DCDB + AC & DC SPD (Type II) | B12: 1 | C12: lot | D12: 8000 | E12: =B12*D12 -> 8000 | F12: Estimate
A13: MCB/MCCB protection (AC & DC side) | B13: 1 | C13: lot | D13: 4000 | E13: =B13*D13 -> 4000 | F13: Estimate
A14: Earthing (module + LA earthing, 2 pits) | B14: 1 | C14: lot | D14: 6000 | E14: =B14*D14 -> 6000 | F14: Estimate; standard 2-pit earthing for residential rooftop
A15: Lightning protection | B15: 1 | C15: lot | D15: 3000 | E15: =B15*D15 -> 3000 | F15: Estimate
A16: External display/monitoring accessory | B16: 1 | C16: lot | D16: 2500 | E16: =B16*D16 -> 2500 | F16: Fusion 63 has built-in WiFi monitoring; this covers optional add-on display
A17: Installation & Engineering
A18: Installation & commissioning labour | B18: 1 | C18: lot | D18: 15000 | E18: =B18*D18 -> 15000 | F18: Estimate; typical for a 5 kW-class rooftop crew job
A19: Transportation | B19: 1 | C19: lot | D19: 3000 | E19: =B19*D19 -> 3000 | F19: Estimate
A20: Engineering/design + net-metering application support | B20: 1 | C20: lot | D20: 8000 | E20: =B20*D20 -> 8000 | F20: Estimate; covers DISCOM liaison and net-metering paperwork
A21: Testing & commissioning documentation | B21: 1 | C21: lot | D21: 3000 | E21: =B21*D21 -> 3000 | F21: Estimate
A23: Subtotal (materials + BOS + installation) | E23: =SUM(E5:E21) -> 236691
A24: Contingency | D24: 0.05 | E24: =E23*D24 -> 11834.55 | F24: Covers minor scope changes/price fluctuation
A26: TOTAL DIRECT PROJECT COST | E26: =E23+E24 -> 248525.55
A28: Commercial Pricing (EPC margin -> customer quotation)
A29: EPC overhead & commercial margin | D29: 0.12 | F29: Typical margin range for residential EPC solar quotes in India is 10-15% over direct cost
A30: GROSS PROJECT PRICE (before subsidy) | E30: =E26*(1+D29) -> 278348.62
A32: PM Surya Ghar Subsidy Application
A33: System size (kWp) | E33: ='Load & Sizing'!B19 -> 5.175
A34: Applicable CFA (residential, >=3kW system => flat cap) | E34: =Assumptions!B26 -> 78000 | F34: System is 5.175 kWp (>3kW) so the flat Rs.78,000 cap applies, not the per-kW slab calculation
A36: NET CUSTOMER INVESTMENT (after subsidy) | E36: =E30-E34 -> 200348.62

Sheet Savings & Financial
A1: Annual Energy Generation, Savings & Financial Analysis
A3: Annual Generation (derived, reconciled against the 6,800 kWh/year target)
A4: DC system size (kWp) | B4: ='Load & Sizing'!B19 -> 5.175
A5: Peak sun hours | B5: =Assumptions!B14 -> 4.5
A6: Performance ratio | B6: =Assumptions!B15 -> 0.8
A7: Estimated annual generation, Year 1 (kWh) | B7: =B4*B5*365*B6 -> 6799.95 | C7: kWp x PSH x 365 x PR. This reconciles to ~6,800 kWh/year (matches the confirmed project baseline, superseding an earlier draft figure of 6,570 kWh which had used 5 kWp nominal instead of the actual 5.175 kWp DC size).
A8: Sanity check: generation yield (kWh/kWp/year) | B8: =B7/B4 -> 1314 | C8: Typical Delhi-NCR rooftop yield range is ~1,300-1,600 kWh/kWp/year; this model's ~1,314 sits at the conservative end, appropriate for a real (non-ideal tilt/orientation, some soiling) residential install rather than a lab-perfect estimate.
A10: Bill Savings (not 1:1 with generation - self-consumption vs. export matters)
A11: Self-consumption share | B11: =Assumptions!B19 -> 0.55
A12: Self-consumed units (kWh/yr) | B12: =B7*B11 -> 3739.9725
A13: Exported units (kWh/yr) | B13: =B7-B12 -> 3059.9775
A14: Retail tariff (Rs./kWh) | B14: =Assumptions!B7 -> 8
A15: Net-metering export credit rate (Rs./kWh) | B15: =Assumptions!B20 -> 6.5
A16: Savings from self-consumption (Rs./yr) | B16: =B12*B14 -> 29919.78
A17: Credit from grid export (Rs./yr) | B17: =B13*B15 -> 19889.854
A18: O&M cost (Rs./yr) | B18: =-Assumptions!B17 -> -2500
A19: NET ANNUAL SAVINGS, Year 1 (Rs.) | B19: =B16+B17+B18 -> 47309.634
A21: Payback & ROI
A22: Net customer investment (Rs., after subsidy) | B22: ='BOM & Costing'!E36 -> 200348.62
A23: SIMPLE PAYBACK (years) | B23: =B22/B19 -> 4.2348376 | C23: Net investment / Year-1 net annual savings. Ignores degradation and tariff escalation - a conservative (slightly pessimistic) simple-payback view.
A25: 25-Year Perspective (accounts for degradation; O&M and one inverter replacement)
A26: Annual module degradation | B26: =Assumptions!B16 -> 0.0055
A27: Inverter replacement cost (Year 12, one-time) | B27: ='BOM & Costing'!D6 -> 42000 | C27: Assumed same as original inverter unit cost
A28: Approx. cumulative net savings over 25 years | B28: =B19*25*(1-B26*12)-B27 -> 1062679.9 | C28: Simplified: Year-1 net savings x 25 years x an average degradation haircut (~12 years' worth of decline, roughly approximating the declining-output curve) minus one inverter replacement. A simplification, not a full year-by-year DCF - flagged as such deliberately (see Financial Analysis note in the report).
A29: Approx. 25-year ROI (on net investment) | B29: =B28/B22 -> 5.3041542
A31: Simple payback vs. DCF: this model deliberately uses SIMPLE payback (investment / year-1 savings) as the headline number, since it's the metric a residential customer actually asks about and is easy to defend. A discounted cash-flow (DCF) view - discounting future savings to present value - would be more rigorous for a large commercial project, but is unnecessary complexity for a small residential case; the 25-year cumulative view above is a lightweight substitute that still credits degradation and one replacement cost, without a full year-by-year model.

Sheet Sensitivity
A1: Sensitivity Analysis
A3: Base case net investment (Rs.) | B3: ='Savings & Financial'!B22 -> 200348.62
A4: Base case tariff (Rs./kWh) | B4: =Assumptions!B7 -> 8
A5: Base case generation (kWh/yr) | B5: ='Savings & Financial'!B7 -> 6799.95
A6: Self-consumption share | B6: =Assumptions!B19 -> 0.55
A7: Export credit rate (Rs./kWh) | B7: =Assumptions!B20 -> 6.5
A8: O&M (Rs./yr) | B8: =-Assumptions!B17 -> -2500
A10: 1. Tariff sensitivity (Low / Base / High) - payback in years
A11: Tariff scenario | B11: Low (Rs.6.5) | C11: Base (Rs.8) | D11: High (Rs.9.5)
A12: Payback (years) | B12: =$B$3/(($B$5*$B$6*6.5)+($B$5*(1-$B$6)*$B$7)+$B$8) -> 4.8045606 | C12: =$B$3/(($B$5*$B$6*8)+($B$5*(1-$B$6)*$B$7)+$B$8) -> 4.2348376 | D12: =$B$3/(($B$5*$B$6*9.5)+($B$5*(1-$B$6)*$B$7)+$B$8) -> 3.7859063
A14: 2. Generation sensitivity (Lower / Base / Higher, e.g. shading/soiling/orientation variance) - payback in years
A15: Generation scenario | B15: Lower (-10%) | C15: Base | D15: Higher (+10%)
A16: Payback (years) | B16: =$B$3/(($B$5*0.9*$B$6*$B$4)+($B$5*0.9*(1-$B$6)*$B$7)+$B$8) -> 4.7331658 | C16: =$B$3/(($B$5*1*$B$6*$B$4)+($B$5*1*(1-$B$6)*$B$7)+$B$8) -> 4.2348376 | D16: =$B$3/(($B$5*1.1*$B$6*$B$4)+($B$5*1.1*(1-$B$6)*$B$7)+$B$8) -> 3.8314463
A18: 3. Project cost sensitivity (Lower / Base / Higher, e.g. component price swing) - payback in years
A19: Cost scenario | B19: Lower (-10%) | C19: Base | D19: Higher (+10%)
A20: Payback (years) | B20: =($B$3*0.9)/(($B$5*$B$6*$B$4)+($B$5*(1-$B$6)*$B$7)+$B$8) -> 3.8113538 | C20: =($B$3*1)/(($B$5*$B$6*$B$4)+($B$5*(1-$B$6)*$B$7)+$B$8) -> 4.2348376 | D20: =($B$3*1.1)/(($B$5*$B$6*$B$4)+($B$5*(1-$B$6)*$B$7)+$B$8) -> 4.6583214
A22: Reading this: payback ranges roughly 3.8 to 4.8 years across realistic tariff/generation/cost variation - the base case (~4.2 years) is not fragile to any single assumption moving by ~10%. This kind of range, not a single point estimate, is what a customer or reviewing manager actually wants to see.

Sheet Alternatives
A1: Alternative Configurations Considered
A3: Criterion | B3: Selected: Waaree Bifacial + Fusion 63 | C3: Alt. 1: Standard Mono-PERC + smaller inverter | D3: Alt. 2: Premium Tier-1 module (e.g. Adani/Premier)
A4: Module efficiency | B4: 22.26% (N-Type TOPCon, bifacial) | C4: ~19-20% (standard Mono-PERC) | D4: ~22-23% (similar tier, premium brand)
A5: Approx. module cost | B5: Rs.11,299 (9 units) | C5: ~15-20% cheaper per Wp | D5: ~10-15% pricier per Wp
A6: Bifacial gain | B6: Present but not counted in this model's generation figure (conservative) | C6: Not applicable | D6: Depends on specific model
A7: Warranty | B7: 12-yr product / 30-yr linear output | C7: Typically 10-12 yr product / 25-yr output | D7: Similar to selected, brand-dependent
A8: Availability (India) | B8: Good - Waaree is a major domestic manufacturer, PM Surya Ghar-eligible | C8: Good, widely available | D8: Good, but marginally higher lead time for premium SKUs
A9: Recommendation | B9: SELECTED - best balance of technical headroom (bifacial, high efficiency) and cost for this customer's budget-conscious priority | C9: Lower upfront cost, but shorter warranty and lower efficiency reduces long-term value | D9: Marginal efficiency gain doesn't justify the premium for a budget-conscious residential customer
A11: The point of this comparison is not to declare one product universally 'best' - it's to show the trade-off reasoning: the selected configuration wins on this specific customer's stated priority (moderate upfront cost, but wants a durable, bankable brand), not on any single spec in isolation.
